cubeplus_sdk/__init__.py
cubeplus_sdk/cli.py
cubeplus_sdk/main.py
cubeplus_sdk-1.0.1.dist-info/METADATA
cubeplus_sdk-1.0.1.dist-info/WHEEL
cubeplus_sdk-1.0.1.dist-info/top_level.txt
cubeplus_sdk-1.0.1.dist-info/RECORD
