Metadata-Version: 2.4
Name: CubePlus-SDK
Version: 1.0.1
Requires-Dist: pydantic>=2.0
Requires-Dist: requests
Requires-Dist: urllib3
Requires-Dist: python-dotenv
Requires-Dist: pyotp
Requires-Dist: websocket-client
Requires-Dist: flask
Requires-Dist: click
